freebox_v5_status/__init__.py
freebox_v5_status/freeboxstatus.py
freebox_v5_status-1.1.1.data/scripts/freebox_show_status.py
freebox_v5_status-1.1.1.data/scripts/freebox_to_graphite.py
freebox_v5_status-1.1.1.dist-info/LICENSE.txt
freebox_v5_status-1.1.1.dist-info/METADATA
freebox_v5_status-1.1.1.dist-info/WHEEL
freebox_v5_status-1.1.1.dist-info/top_level.txt
freebox_v5_status-1.1.1.dist-info/RECORD
