Metadata-Version: 2.1
Name: freebox-v5-status
Version: 1.1.1
Summary: Parse Freebox V5 status page
Home-page: http://github.com/demikl/freeboxv5-status
Author: Mickael Le Baillif
Author-email: mickael.le.baillif@gmail.com
License: MIT
Keywords: freebox adsl
Platform: UNKNOWN
